{"krzp5ZIp1soJkW07u7kemQ==":"_mg-7040-2000x1333.jpeg","Q90I92DSEXPDEsbNeAHJXQ==":"_mg-7041-2000x1333.jpeg","/5TxP6rB5Xsj6wML99MSww==":"logo2.png","dZjZpH2jNcPmG97PXxJmjA==":"_mg-6268-2000x1370.jpeg","tsIgiw9c/AjMiEAwqcPdgA==":"_mg-6269-2000x1370.jpeg","FjcFN+Y2fj+k8I11e6w2ZA==":"_mg-6270-2000x1370.jpeg","yjvagX4Z0v78YetOQzIErg==":"_mg-6278-2000x1618.jpeg","WyEbi19gXiVo4fMdtqDmGQ==":"_mg-7023-1162x1473.jpeg","h5GXp2Rmfts572QDSIZKLQ==":"_mg-5563-696x464.jpg","31W+5uHYCD2Yum3B6wI0mg==":"_mg-6929-696x464.jpg","oIHQur+qRixqOuc3Bk1kYw==":"_mg-6988-696x464.jpg","BteUl6/fIKCxjdHEs1b01g==":"_mg-6973-696x464.jpg"}